larper/__init__.py
larper/parser.py
larper/scraper.py
larper/version.py
larper/__pycache__/__init__.cpython-312.pyc
larper/__pycache__/parser.cpython-312.pyc
larper/__pycache__/scraper.cpython-312.pyc
larper/__pycache__/version.cpython-312.pyc
larper-0.2511.0.dist-info/licenses/LICENSE
larper-0.2511.0.dist-info/METADATA
larper-0.2511.0.dist-info/WHEEL
larper-0.2511.0.dist-info/top_level.txt
larper-0.2511.0.dist-info/RECORD
