Metadata-Version: 2.4
Name: larper
Version: 0.2511.0
Summary: Larper - LinkedIn API Response Parser
Author-email: "Rodrigo Martínez (brunneis)" <dev@brunneis.com>
License: GNU General Public License v3 (GPLv3)
Project-URL: Homepage, https://github.com/brunneis/larper
Classifier: Development Status :: 4 - Beta
Classifier: Environment :: Console
Classifier: Intended Audience :: Developers
Classifier: License :: OSI Approved :: GNU General Public License v3 (GPLv3)
Classifier: Operating System :: POSIX :: Linux
Classifier: Programming Language :: Python :: 3.10
Classifier: Programming Language :: Python :: Implementation :: PyPy
Classifier: Topic :: Software Development :: Libraries :: Python Modules
Requires-Python: >=3.10
License-File: LICENSE
Requires-Dist: requests>=2.31.0
Dynamic: license-file
